README.rst
free.py
setup.py
macos_free.egg-info/PKG-INFO
macos_free.egg-info/SOURCES.txt
macos_free.egg-info/dependency_links.txt
macos_free.egg-info/entry_points.txt
macos_free.egg-info/not-zip-safe
macos_free.egg-info/requires.txt
macos_free.egg-info/top_level.txt